aplusml/__init__.py
aplusml/config.py
aplusml/draw.py
aplusml/models.py
aplusml/parse.py
aplusml/plot.py
aplusml/run.py
aplusml/sim.py
aplusml-0.3.1.dist-info/LICENSE
aplusml-0.3.1.dist-info/METADATA
aplusml-0.3.1.dist-info/WHEEL
aplusml-0.3.1.dist-info/RECORD
