Metadata-Version: 2.3
Name: aplusml
Version: 0.3.1
Summary: Conduct usefulness simulations of ML models embedded in workflows
License: Apache 2.0
Author: Michael Wornow
Requires-Python: >=3.10
Classifier: License :: Other/Proprietary License
Classifier: Programming Language :: Python :: 3
Classifier: Programming Language :: Python :: 3.10
Classifier: Programming Language :: Python :: 3.11
Classifier: Programming Language :: Python :: 3.12
Classifier: Programming Language :: Python :: 3.13
Provides-Extra: dev
Requires-Dist: contourpy (==1.0.7)
Requires-Dist: cycler (==0.11.0)
Requires-Dist: dill (==0.3.6)
Requires-Dist: fast-histogram (==0.11)
Requires-Dist: fonttools (==4.38.0)
Requires-Dist: joblib (==1.2.0)
Requires-Dist: jupyter (==1.0.0)
Requires-Dist: jupyterlab (==3.5.2)
Requires-Dist: kiwisolver (==1.4.4)
Requires-Dist: matplotlib (==3.8.0)
Requires-Dist: mizani (==0.13.0)
Requires-Dist: mpire (==2.6.0)
Requires-Dist: mpl-scatter-density (==0.7)
Requires-Dist: multiprocess (==0.70.14)
Requires-Dist: numpy (<2.0)
Requires-Dist: oyaml (==1.0)
Requires-Dist: packaging (==25.0)
Requires-Dist: palettable (==3.3.0)
Requires-Dist: pandas (==2.2.0)
Requires-Dist: patsy (==0.5.3)
Requires-Dist: pillow (==9.4.0)
Requires-Dist: plotnine (==0.14.5)
Requires-Dist: pydot (==1.4.2)
Requires-Dist: pygments (==2.17)
Requires-Dist: pyparsing (==3.0.9)
Requires-Dist: python-dateutil (==2.8.2)
Requires-Dist: pytz (==2022.7.1)
Requires-Dist: pyyaml (==6.0)
Requires-Dist: ruamel-yaml (==0.17.21)
Requires-Dist: ruamel-yaml-clib (==0.2.7)
Requires-Dist: scikit-learn (==1.2.0)
Requires-Dist: seaborn (==0.12.2)
Requires-Dist: simpy (==4.0.1)
Requires-Dist: six (==1.16.0)
Requires-Dist: sphinx (==8.1.3) ; extra == "dev"
Requires-Dist: sphinx-rtd-theme (==3.0.2) ; extra == "dev"
Requires-Dist: statsmodels (==0.14)
Requires-Dist: threadpoolctl (==3.1.0)
Requires-Dist: tqdm (==4.64.1)
Project-URL: Bug Tracker, https://github.com/som-shahlab/aplusml/issues
Project-URL: Homepage, https://github.com/som-shahlab/aplusml
